ansys/api/pyensight/VERSION
ansys/api/pyensight/__init__.py
ansys/api/pyensight/access_assets.py
ansys/api/pyensight/calc_funcs.py
ansys/api/pyensight/calc_math.py
ansys/api/pyensight/dvs_api.py
ansys/api/pyensight/ens_animobj.py
ansys/api/pyensight/ens_annot.py
ansys/api/pyensight/ens_annot_arrow.py
ansys/api/pyensight/ens_annot_dial.py
ansys/api/pyensight/ens_annot_gauge.py
ansys/api/pyensight/ens_annot_lgnd.py
ansys/api/pyensight/ens_annot_line.py
ansys/api/pyensight/ens_annot_logo.py
ansys/api/pyensight/ens_annot_marker.py
ansys/api/pyensight/ens_annot_shape.py
ansys/api/pyensight/ens_annot_text.py
ansys/api/pyensight/ens_camera.py
ansys/api/pyensight/ens_case.py
ansys/api/pyensight/ens_emitterobj.py
ansys/api/pyensight/ens_flipbook.py
ansys/api/pyensight/ens_frame.py
ansys/api/pyensight/ens_geom.py
ansys/api/pyensight/ens_globals.py
ansys/api/pyensight/ens_group.py
ansys/api/pyensight/ens_lightsource.py
ansys/api/pyensight/ens_lpart.py
ansys/api/pyensight/ens_mat.py
ansys/api/pyensight/ens_palette.py
ansys/api/pyensight/ens_part.py
ansys/api/pyensight/ens_part_aux_geom.py
ansys/api/pyensight/ens_part_axisymmetric.py
ansys/api/pyensight/ens_part_built_up.py
ansys/api/pyensight/ens_part_clip.py
ansys/api/pyensight/ens_part_contour.py
ansys/api/pyensight/ens_part_developed_surface.py
ansys/api/pyensight/ens_part_discrete_particle.py
ansys/api/pyensight/ens_part_elevated_surface.py
ansys/api/pyensight/ens_part_filter.py
ansys/api/pyensight/ens_part_frame.py
ansys/api/pyensight/ens_part_fx_sep_att.py
ansys/api/pyensight/ens_part_fx_shock.py
ansys/api/pyensight/ens_part_fx_vortex_core.py
ansys/api/pyensight/ens_part_isosurface.py
ansys/api/pyensight/ens_part_mat_interface.py
ansys/api/pyensight/ens_part_model.py
ansys/api/pyensight/ens_part_particle_trace.py
ansys/api/pyensight/ens_part_point.py
ansys/api/pyensight/ens_part_profile.py
ansys/api/pyensight/ens_part_tensor_glyph.py
ansys/api/pyensight/ens_part_vector_arrow.py
ansys/api/pyensight/ens_part_vof.py
ansys_api_pyensight-0.4.11.dist-info/licenses/LICENSE
ansys_api_pyensight-0.4.11.dist-info/METADATA
ansys_api_pyensight-0.4.11.dist-info/WHEEL
ansys_api_pyensight-0.4.11.dist-info/entry_points.txt
ansys_api_pyensight-0.4.11.dist-info/top_level.txt
ansys_api_pyensight-0.4.11.dist-info/RECORD
