Metadata-Version: 2.4
Name: ansys-api-pyensight
Version: 0.4.11
Summary: Autogenerated python gRPC interface package for ansys-api-pyensight, built on 10:08:38 on 22 January 2026
Home-page: https://github.com/ansys/ansys-api-pyensight
Author: ANSYS, Inc.
Author-email: pyansys.core@ansys.com
Maintainer: ANSYS, Inc.
Maintainer-email: pyansys.core@ansys.com
License: MIT
Requires-Python: >=3.9
License-File: LICENSE
Requires-Dist: grpcio>=1.17
Requires-Dist: protobuf>=3.19
Dynamic: author
Dynamic: author-email
Dynamic: description
Dynamic: description-content-type
Dynamic: home-page
Dynamic: license
Dynamic: license-file
Dynamic: maintainer
Dynamic: maintainer-email
Dynamic: requires-dist
Dynamic: requires-python
Dynamic: summary
